hemlock_demographics/__init__.py
hemlock_demographics/languages.py
hemlock_demographics-0.0.8.dist-info/LICENSE
hemlock_demographics-0.0.8.dist-info/METADATA
hemlock_demographics-0.0.8.dist-info/WHEEL
hemlock_demographics-0.0.8.dist-info/top_level.txt
hemlock_demographics-0.0.8.dist-info/RECORD
