Metadata-Version: 2.1
Name: hemlock-demographics
Version: 0.0.8
Summary: Hemlock extension for demographic information
Home-page: https://dsbowen.github.io/hemlock-demographics
Author: Dillon Bowen
Author-email: dsbowen@wharton.upenn.edu
License: UNKNOWN
Platform: UNKNOWN
Classifier: Programming Language :: Python :: 3
Classifier: License :: OSI Approved :: MIT License
Classifier: Operating System :: OS Independent
Requires-Python: >=3.6
Requires-Dist: country-list (>=0.2.1)
